eduvpn/__init__.py
eduvpn/brand.py
eduvpn/config.py
eduvpn/crypto.py
eduvpn/exceptions.py
eduvpn/images.py
eduvpn/io.py
eduvpn/main.py
eduvpn/manager.py
eduvpn/metadata.py
eduvpn/notify.py
eduvpn/oauth2.py
eduvpn/openvpn.py
eduvpn/other_nm.py
eduvpn/remote.py
eduvpn/ui.py
eduvpn/util.py
eduvpn/actions/__init__.py
eduvpn/actions/activate.py
eduvpn/actions/add.py
eduvpn/actions/delete.py
eduvpn/actions/select.py
eduvpn/actions/switch.py
eduvpn/actions/vpn_status.py
eduvpn/steps/__init__.py
eduvpn/steps/browser.py
eduvpn/steps/custom_url.py
eduvpn/steps/fetching.py
eduvpn/steps/finalize.py
eduvpn/steps/instance.py
eduvpn/steps/messages.py
eduvpn/steps/parse_config.py
eduvpn/steps/profile.py
eduvpn/steps/provider.py
eduvpn/steps/reauth.py
eduvpn/steps/start.py
eduvpn/steps/totp_enroll.py
eduvpn/steps/two_way_auth.py
eduvpn/steps/yubi_enroll.py
letsconnect_client-1.0rc16.data/data/share/applications/letsconnect.desktop
letsconnect_client-1.0rc16.data/data/share/eduvpn/eduvpn.png
letsconnect_client-1.0rc16.data/data/share/eduvpn/institute.png
letsconnect_client-1.0rc16.data/data/share/eduvpn/institute_small.png
letsconnect_client-1.0rc16.data/data/share/eduvpn/internet.png
letsconnect_client-1.0rc16.data/data/share/eduvpn/internet_small.png
letsconnect_client-1.0rc16.data/data/share/eduvpn/builder/2fa.ui
letsconnect_client-1.0rc16.data/data/share/eduvpn/builder/connection_type.ui
letsconnect_client-1.0rc16.data/data/share/eduvpn/builder/custom_url.ui
letsconnect_client-1.0rc16.data/data/share/eduvpn/builder/fetch.ui
letsconnect_client-1.0rc16.data/data/share/eduvpn/builder/instances.ui
letsconnect_client-1.0rc16.data/data/share/eduvpn/builder/profiles.ui
letsconnect_client-1.0rc16.data/data/share/eduvpn/builder/redirecturl.ui
letsconnect_client-1.0rc16.data/data/share/eduvpn/builder/token.ui
letsconnect_client-1.0rc16.data/data/share/eduvpn/builder/totp_enroll.ui
letsconnect_client-1.0rc16.dist-info/METADATA
letsconnect_client-1.0rc16.dist-info/RECORD
letsconnect_client-1.0rc16.dist-info/WHEEL
letsconnect_client-1.0rc16.dist-info/entry_points.txt
letsconnect_client-1.0rc16.dist-info/top_level.txt
