Metadata-Version: 2.1
Name: letsconnect-client
Version: 1.0rc16
Summary: Let's Connect! client
Home-page: https://github.com/eduvpn/python-eduvpn-client
Author: Gijs Molenaar
Author-email: gijs@pythonic.nl
License: GPL3
Keywords: vpn openvpn networking security
Platform: UNKNOWN
Classifier: Development Status :: 5 - Production/Stable
Classifier: License :: OSI Approved :: GNU General Public License v3 (GPLv3)
Classifier: Operating System :: POSIX
Classifier: Programming Language :: Python
Classifier: Programming Language :: Python :: 2
Classifier: Programming Language :: Python :: 2.7
Classifier: Programming Language :: Python :: 3
Classifier: Programming Language :: Python :: 3.4
Classifier: Programming Language :: Python :: 3.5
Classifier: Programming Language :: Python :: 3.6
Classifier: Programming Language :: Python :: 3.7
Classifier: Topic :: System :: Operating System Kernels :: Linux
Classifier: Topic :: System :: Networking
Classifier: Environment :: X11 Applications
Provides-Extra: client
Provides-Extra: test-online
Requires-Dist: requests
Requires-Dist: pynacl
Requires-Dist: requests-oauthlib
Requires-Dist: future
Requires-Dist: python-dateutil
Requires-Dist: six
Requires-Dist: repoze.lru
Requires-Dist: qrcode
Requires-Dist: pillow
Requires-Dist: cryptography
Provides-Extra: client
Requires-Dist: dbus-python; extra == 'client'
Requires-Dist: pygobject; extra == 'client'
Provides-Extra: test-online
Requires-Dist: mechanicalsoup; extra == 'test-online'
Requires-Dist: futures; extra == 'test-online'
